app_store_notifications_v2_validator/__init__.py
app_store_notifications_v2_validator-0.0.9.dist-info/LICENSE
app_store_notifications_v2_validator-0.0.9.dist-info/METADATA
app_store_notifications_v2_validator-0.0.9.dist-info/WHEEL
app_store_notifications_v2_validator-0.0.9.dist-info/top_level.txt
app_store_notifications_v2_validator-0.0.9.dist-info/RECORD
