Metadata-Version: 2.1
Name: app-store-notifications-v2-validator
Version: 0.0.9
Summary: AppStore notifications v2 Validator
Home-page: https://github.com/rickwierenga/app-store-notifications-v2-validator
Author: Rick Wierenga
Author-email: rick_wierenga@icloud.com
Project-URL: Bug Tracker, https://github.com/rickwierenga/app-store-notifications-v2-validator/issues
Classifier: Programming Language :: Python :: 3
Classifier: License :: OSI Approved :: MIT License
Classifier: Operating System :: OS Independent
Requires-Python: >=3.6
License-File: LICENSE
Requires-Dist: cffi >=1.15.1
Requires-Dist: cryptography >=40.0.2
Requires-Dist: pycparser >=2.21
Requires-Dist: PyJWT >=2.7.0
Requires-Dist: pyOpenSSL >=23.1.1
